jupyterlab_mpi_job_launcher/__init__.py
jupyterlab_mpi_job_launcher/_version.py
jupyterlab_mpi_job_launcher/config.py
jupyterlab_mpi_job_launcher/handlers.py
jupyterlab_mpi_job_launcher/mpi_job_handler.py
jupyterlab_mpi_job_launcher/labextension/build_log.json
jupyterlab_mpi_job_launcher/labextension/package.json
jupyterlab_mpi_job_launcher/labextension/schemas/jupyterlab-mpi-job-launcher/package.json.orig
jupyterlab_mpi_job_launcher/labextension/schemas/jupyterlab-mpi-job-launcher/plugin.json
jupyterlab_mpi_job_launcher/labextension/static/lib_index_js.6fd6dd264a3e856293bf.js
jupyterlab_mpi_job_launcher/labextension/static/lib_index_js.6fd6dd264a3e856293bf.js.map
jupyterlab_mpi_job_launcher/labextension/static/node_modules_emotion_use-insertion-effect-with-fallbacks_dist_emotion-use-insertion-effect-wi-3c9bb40.667fd1a3777106c9bfb0.js
jupyterlab_mpi_job_launcher/labextension/static/node_modules_emotion_use-insertion-effect-with-fallbacks_dist_emotion-use-insertion-effect-wi-3c9bb40.667fd1a3777106c9bfb0.js.map
jupyterlab_mpi_job_launcher/labextension/static/node_modules_emotion_use-insertion-effect-with-fallbacks_dist_emotion-use-insertion-effect-wi-3c9bb41.1cb4dbd84be7ee328df7.js
jupyterlab_mpi_job_launcher/labextension/static/node_modules_emotion_use-insertion-effect-with-fallbacks_dist_emotion-use-insertion-effect-wi-3c9bb41.1cb4dbd84be7ee328df7.js.map
jupyterlab_mpi_job_launcher/labextension/static/remoteEntry.30c14d8ac61d95b86f64.js
jupyterlab_mpi_job_launcher/labextension/static/remoteEntry.30c14d8ac61d95b86f64.js.map
jupyterlab_mpi_job_launcher/labextension/static/style.js
jupyterlab_mpi_job_launcher/labextension/static/style_index_js.f91c4905c48f5365b575.js
jupyterlab_mpi_job_launcher/labextension/static/style_index_js.f91c4905c48f5365b575.js.map
jupyterlab_mpi_job_launcher/labextension/static/vendors-node_modules_babel_runtime_helpers_esm_extends_js-node_modules_emotion_serialize_dist-051195.f4cbf7d78ae75ca37e05.js
jupyterlab_mpi_job_launcher-0.2.5.dist-info/METADATA
jupyterlab_mpi_job_launcher-0.2.5.dist-info/WHEEL
jupyterlab_mpi_job_launcher-0.2.5.dist-info/licenses/LICENSE
jupyterlab_mpi_job_launcher-0.2.5.dist-info/RECORD
