Metadata-Version: 2.4
Name: jupyterlab_mpi_job_launcher
Version: 0.2.5
Summary: A JupyterLab extension.
Project-URL: Homepage, https://github.com/Navteca/jupyterlab-mpi-job-launcher
Project-URL: Bug Tracker, https://github.com/Navteca/jupyterlab-mpi-job-launcher/issues
Project-URL: Repository, https://github.com/Navteca/jupyterlab-mpi-job-launcher.git
Author-email: Navteca LLC <info@navteca.com>
License: BSD 3-Clause License
License-File: LICENSE
Keywords: jupyter,jupyterlab,jupyterlab-extension
Classifier: Framework :: Jupyter
Classifier: Framework :: Jupyter :: JupyterLab
Classifier: Framework :: Jupyter :: JupyterLab :: 4
Classifier: Framework :: Jupyter :: JupyterLab :: Extensions
Classifier: Framework :: Jupyter :: JupyterLab :: Extensions :: Prebuilt
Classifier: License :: OSI Approved :: BSD License
Classifier: Programming Language :: Python
Classifier: Programming Language :: Python :: 3
Classifier: Programming Language :: Python :: 3.9
Classifier: Programming Language :: Python :: 3.10
Classifier: Programming Language :: Python :: 3.11
Classifier: Programming Language :: Python :: 3.12
Classifier: Programming Language :: Python :: 3.13
Requires-Python: >=3.9
Requires-Dist: grpcio-tools==1.68.1
Requires-Dist: grpcio==1.68.1
Requires-Dist: jupyter-server<3,>=2.4.0
Requires-Dist: loguru
Requires-Dist: pydantic
Requires-Dist: pydantic-settings
Requires-Dist: python-dotenv
Provides-Extra: test
Requires-Dist: coverage; extra == 'test'
Requires-Dist: pytest; extra == 'test'
Requires-Dist: pytest-asyncio; extra == 'test'
Requires-Dist: pytest-cov; extra == 'test'
Requires-Dist: pytest-jupyter[server]>=0.6.0; extra == 'test'
